forgestafftoolbar/__init__.py
forgestafftoolbar/core.py
forgestafftoolbar/links.py
forgestafftoolbar/settings.py
forgestafftoolbar/templates/stafftoolbar/stafftoolbar.html
forgestafftoolbar/templatetags/__init__.py
forgestafftoolbar/templatetags/stafftoolbar.py
forge_stafftoolbar-0.3.1.dist-info/METADATA
forge_stafftoolbar-0.3.1.dist-info/WHEEL
forge_stafftoolbar-0.3.1.dist-info/RECORD
